hvym_stellar/__init__.py
hvym_stellar-0.12.dist-info/licenses/LICENSE
hvym_stellar-0.12.dist-info/WHEEL
hvym_stellar-0.12.dist-info/METADATA
hvym_stellar-0.12.dist-info/RECORD
