Metadata-Version: 2.4
Name: hvym_stellar
Version: 0.12
Summary: Heavymeta Stellar Utilities for Python , By: Fibo Metavinci
Author-email: Fibo Metavinci <pszdw-75nat-5227i-bha5s-y7lai-pebdq-o2agp-3xho4-hd6z6-emxrd-nqe@dmail.ai>
License-Expression: MIT
License-File: LICENSE
Requires-Dist: annotated-types>=0.7.0
Requires-Dist: certifi>=2025.4.26
Requires-Dist: cffi>=1.17.1
Requires-Dist: charset-normalizer>=3.4.2
Requires-Dist: docutils>=0.21.2
Requires-Dist: idna>=3.10
Requires-Dist: mnemonic>=0.20
Requires-Dist: pycparser>=2.22
Requires-Dist: pydantic>=2.11.5
Requires-Dist: pydantic_core>=2.33.2
Requires-Dist: pymacaroons>=0.13.0
Requires-Dist: PyNaCl>=1.5.0
Requires-Dist: requests>=2.32.4
Requires-Dist: requests-sse>=0.5.1
Requires-Dist: six>=1.17.0
Requires-Dist: stellar-sdk>=12.3.0
Requires-Dist: toml>=0.10.2
Requires-Dist: tomli_w>=1.2.0
Requires-Dist: typing-inspection>=0.4.1
Requires-Dist: typing_extensions>=4.14.0
Requires-Dist: urllib3>=2.5.0
Requires-Dist: xdrlib3>=0.1.1
Project-URL: Home, https://github.com/inviti8/hvym_stellar
